colins/__init__.py
colins/blueprint/__init__.py
colins/blueprint/base.py
colins/blueprint/news.py
colins/exceptions.py
colins/scrapers/__init__.py
colins/scrapers/base_scraper.py
colins/scrapers/news_scraper.py
colins-0.0.1b1.dist-info/WHEEL
colins-0.0.1b1.dist-info/METADATA
colins-0.0.1b1.dist-info/RECORD
